{
  "file": "PPT Performance Appraisal 2023-2024.md",
  "source_doc": "PPT Performance Appraisal 2023-2024.pdf",
  "anchors": [
    {
      "id": "S0.p1",
      "page": 0,
      "paragraph_index": 1,
      "char_start": 80,
      "char_end": 128
    },
    {
      "id": "S0.p2",
      "page": 0,
      "paragraph_index": 2,
      "char_start": 158,
      "char_end": 334
    },
    {
      "id": "S1.p1",
      "page": 1,
      "paragraph_index": 1,
      "char_start": 395,
      "char_end": 591
    },
    {
      "id": "S2.p1",
      "page": 2,
      "paragraph_index": 1,
      "char_start": 695,
      "char_end": 786
    },
    {
      "id": "S3.p1",
      "page": 3,
      "paragraph_index": 1,
      "char_start": 844,
      "char_end": 1000
    },
    {
      "id": "S3.p2",
      "page": 3,
      "paragraph_index": 2,
      "char_start": 1048,
      "char_end": 1237
    },
    {
      "id": "S4.p1",
      "page": 4,
      "paragraph_index": 1,
      "char_start": 1301,
      "char_end": 1904
    },
    {
      "id": "S5.p1",
      "page": 5,
      "paragraph_index": 1,
      "char_start": 2065,
      "char_end": 2614
    },
    {
      "id": "S5.p2",
      "page": 5,
      "paragraph_index": 2,
      "char_start": 2624,
      "char_end": 2718
    },
    {
      "id": "S5.p3",
      "page": 5,
      "paragraph_index": 3,
      "char_start": 2748,
      "char_end": 2800
    },
    {
      "id": "S6.p1",
      "page": 6,
      "paragraph_index": 1,
      "char_start": 2976,
      "char_end": 3321
    },
    {
      "id": "S7.p1",
      "page": 7,
      "paragraph_index": 1,
      "char_start": 3331,
      "char_end": 3365
    },
    {
      "id": "S8.p1",
      "page": 8,
      "paragraph_index": 1,
      "char_start": 3491,
      "char_end": 4217
    },
    {
      "id": "S9.p1",
      "page": 9,
      "paragraph_index": 1,
      "char_start": 4228,
      "char_end": 4365
    },
    {
      "id": "S10.p1",
      "page": 10,
      "paragraph_index": 1,
      "char_start": 4416,
      "char_end": 4759
    },
    {
      "id": "S11.p1",
      "page": 11,
      "paragraph_index": 1,
      "char_start": 4981,
      "char_end": 5074
    },
    {
      "id": "S12.p1",
      "page": 12,
      "paragraph_index": 1,
      "char_start": 5169,
      "char_end": 5651
    },
    {
      "id": "S13.p1",
      "page": 13,
      "paragraph_index": 1,
      "char_start": 5709,
      "char_end": 5780
    },
    {
      "id": "S14.p1",
      "page": 14,
      "paragraph_index": 1,
      "char_start": 5807,
      "char_end": 5818
    },
    {
      "id": "S15.p1",
      "page": 15,
      "paragraph_index": 1,
      "char_start": 5868,
      "char_end": 6154
    },
    {
      "id": "S15.p2",
      "page": 15,
      "paragraph_index": 2,
      "char_start": 6215,
      "char_end": 6576
    },
    {
      "id": "S16.p1",
      "page": 16,
      "paragraph_index": 1,
      "char_start": 6624,
      "char_end": 7235
    }
  ]
}